calculator_beau28713/__init__.py
calculator_beau28713/__main__.py
calculator_beau28713-0.1.3.dist-info/LICENSE
calculator_beau28713-0.1.3.dist-info/METADATA
calculator_beau28713-0.1.3.dist-info/WHEEL
calculator_beau28713-0.1.3.dist-info/RECORD
