Metadata-Version: 2.1
Name: calculator-beau28713
Version: 0.1.3
Summary: Simple gui calculator that does basic math
Author: Beau
Author-email: beau28713@gmail.com
Requires-Python: >=3.9,<4.0
Classifier: Programming Language :: Python :: 3
Classifier: Programming Language :: Python :: 3.9
Classifier: Programming Language :: Python :: 3.10
Classifier: Programming Language :: Python :: 3.11
Requires-Dist: Kivy (>=2.2.1,<3.0.0)
